closure_linter/__init__.py
closure_linter/aliaspass.py
closure_linter/aliaspass_test.py
closure_linter/checker.py
closure_linter/checkerbase.py
closure_linter/closurizednamespacesinfo.py
closure_linter/closurizednamespacesinfo_test.py
closure_linter/ecmalintrules.py
closure_linter/ecmametadatapass.py
closure_linter/error_check.py
closure_linter/error_fixer.py
closure_linter/error_fixer_test.py
closure_linter/errorrecord.py
closure_linter/errorrules.py
closure_linter/errorrules_test.py
closure_linter/errors.py
closure_linter/fixjsstyle.py
closure_linter/fixjsstyle_test.py
closure_linter/full_test.py
closure_linter/gjslint.py
closure_linter/indentation.py
closure_linter/javascriptlintrules.py
closure_linter/javascriptstatetracker.py
closure_linter/javascriptstatetracker_test.py
closure_linter/javascripttokenizer.py
closure_linter/javascripttokens.py
closure_linter/not_strict_test.py
closure_linter/requireprovidesorter.py
closure_linter/requireprovidesorter_test.py
closure_linter/runner.py
closure_linter/runner_test.py
closure_linter/scopeutil.py
closure_linter/scopeutil_test.py
closure_linter/statetracker.py
closure_linter/statetracker_test.py
closure_linter/strict_test.py
closure_linter/testutil.py
closure_linter/tokenutil.py
closure_linter/tokenutil_test.py
closure_linter/typeannotation.py
closure_linter/typeannotation_test.py
closure_linter/common/__init__.py
closure_linter/common/error.py
closure_linter/common/erroraccumulator.py
closure_linter/common/errorhandler.py
closure_linter/common/erroroutput.py
closure_linter/common/filetestcase.py
closure_linter/common/htmlutil.py
closure_linter/common/lintrunner.py
closure_linter/common/matcher.py
closure_linter/common/position.py
closure_linter/common/simplefileflags.py
closure_linter/common/tokenizer.py
closure_linter/common/tokens.py
closure_linter/common/tokens_test.py
closure_linter-2.3.19.dist-info/DESCRIPTION.rst
closure_linter-2.3.19.dist-info/METADATA
closure_linter-2.3.19.dist-info/RECORD
closure_linter-2.3.19.dist-info/WHEEL
closure_linter-2.3.19.dist-info/entry_points.txt
closure_linter-2.3.19.dist-info/metadata.json
closure_linter-2.3.19.dist-info/top_level.txt
