Metadata-Version: 2.0
Name: closure-linter
Version: 2.3.19
Summary: Closure Linter
Home-page: https://github.com/google/closure-linter
Author: The Closure Linter Authors
Author-email: opensource@google.com
License: Apache
Platform: UNKNOWN
Requires-Dist: python-gflags
